<annotation>
	<folder>JPEGImages</folder>
	<filename>000071.jpg</filename>
	<path>J:\fuhan\data\traindata\alldata\JPEGImages\000071.jpg</path>
	<source>
		<database>Unknown</database>
	</source>
	<size>
		<width>512</width>
		<height>512</height>
		<depth>3</depth>
	</size>
	<segmented>0</segmented>
	<object>
		<name>school</name>
		<pose>Unspecified</pose>
		<truncated>0</truncated>
		<difficult>0</difficult>
		<bndbox>
			<xmin>152</xmin>
			<ymin>296</ymin>
			<xmax>202</xmax>
			<ymax>358</ymax>
		</bndbox>
	</object>
	<object>
		<name>school</name>
		<pose>Unspecified</pose>
		<truncated>0</truncated>
		<difficult>0</difficult>
		<bndbox>
			<xmin>281</xmin>
			<ymin>261</ymin>
			<xmax>430</xmax>
			<ymax>341</ymax>
		</bndbox>
	</object>
</annotation>
