<annotation>
	<folder>JPEGImages</folder>
	<filename>000377.jpg</filename>
	<path>J:\fuhan\data\traindata\alldata\JPEGImages\000377.jpg</path>
	<source>
		<database>Unknown</database>
	</source>
	<size>
		<width>512</width>
		<height>512</height>
		<depth>3</depth>
	</size>
	<segmented>0</segmented>
	<object>
		<name>school</name>
		<pose>Unspecified</pose>
		<truncated>0</truncated>
		<difficult>0</difficult>
		<bndbox>
			<xmin>244</xmin>
			<ymin>252</ymin>
			<xmax>303</xmax>
			<ymax>329</ymax>
		</bndbox>
	</object>
</annotation>
